beakerx_groovy/__init__.py
beakerx_groovy/_version.py
beakerx_groovy/commands.py
beakerx_groovy/install.py
beakerx_groovy/kernel/kernel.json
beakerx_groovy/kernel/logo-32x32.png
beakerx_groovy/kernel/logo-64x64.png
beakerx_groovy/kernel/ext/beakerx-runtimetools-2.0-SNAPSHOT.jar
beakerx_groovy/kernel/lib/annotations-13.0.jar
beakerx_groovy/kernel/lib/ant-1.10.7.jar
beakerx_groovy/kernel/lib/ant-antlr-1.10.7.jar
beakerx_groovy/kernel/lib/ant-junit-1.10.7.jar
beakerx_groovy/kernel/lib/ant-launcher-1.10.7.jar
beakerx_groovy/kernel/lib/antlr4-runtime-4.5.jar
beakerx_groovy/kernel/lib/assertj-core-3.6.1.jar
beakerx_groovy/kernel/lib/beakerx-kernel-base-2.0-SNAPSHOT.jar
beakerx_groovy/kernel/lib/beakerx-kernel-base-api-2.0-SNAPSHOT.jar
beakerx_groovy/kernel/lib/commons-beanutils-1.9.3.jar
beakerx_groovy/kernel/lib/commons-cli-1.2.jar
beakerx_groovy/kernel/lib/commons-codec-1.10.jar
beakerx_groovy/kernel/lib/commons-collections-3.2.2.jar
beakerx_groovy/kernel/lib/commons-io-2.5.jar
beakerx_groovy/kernel/lib/commons-lang3-3.6.jar
beakerx_groovy/kernel/lib/commons-logging-1.2.jar
beakerx_groovy/kernel/lib/commons-text-1.1.jar
beakerx_groovy/kernel/lib/fluent-hc-4.5.5.jar
beakerx_groovy/kernel/lib/groovy-3.0.3.jar
beakerx_groovy/kernel/lib/groovy-ant-3.0.3.jar
beakerx_groovy/kernel/lib/groovy-astbuilder-3.0.3.jar
beakerx_groovy/kernel/lib/groovy-cli-picocli-3.0.3.jar
beakerx_groovy/kernel/lib/groovy-console-3.0.3.jar
beakerx_groovy/kernel/lib/groovy-datetime-3.0.3.jar
beakerx_groovy/kernel/lib/groovy-docgenerator-3.0.3.jar
beakerx_groovy/kernel/lib/groovy-groovydoc-3.0.3.jar
beakerx_groovy/kernel/lib/groovy-groovysh-3.0.3.jar
beakerx_groovy/kernel/lib/groovy-jmx-3.0.3.jar
beakerx_groovy/kernel/lib/groovy-json-3.0.3.jar
beakerx_groovy/kernel/lib/groovy-jsr223-3.0.3.jar
beakerx_groovy/kernel/lib/groovy-macro-3.0.3.jar
beakerx_groovy/kernel/lib/groovy-nio-3.0.3.jar
beakerx_groovy/kernel/lib/groovy-servlet-3.0.3.jar
beakerx_groovy/kernel/lib/groovy-sql-3.0.3.jar
beakerx_kernel_groovy-2.0.0.dist-info/METADATA
beakerx_kernel_groovy-2.0.0.dist-info/WHEEL
beakerx_kernel_groovy-2.0.0.dist-info/entry_points.txt
beakerx_kernel_groovy-2.0.0.dist-info/top_level.txt
beakerx_kernel_groovy-2.0.0.dist-info/RECORD
